Workbook

Sheet Cover
A1: AWL AGRIBUSINESS LIMITED
B2: Financial Statement Analysis Workbook
B3: COMPANY & WORKBOOK INFORMATION
B4: Company Name | C4: AWL Agri Business Limited (formerly Adani Wilmar Ltd)
B5: Stock Exchange | C5: NSE: AWL | BSE: 543458
B6: Sector / Industry | C6: FMCG - Agricultural Food & Other Products
B7: Headquarters | C7: Ahmedabad, Gujarat, India
B8: Reporting Currency | C8: Indian Rupees (Rs.), in Crores
B9: Financial Statements Basis | C9: Consolidated
B10: Period Covered | C10: FY2021-22 to FY2025-26 (5 Financial Years)
B11: Workbook Prepared On | C11: 46208
B12: Prepared By | C12: Yashu Mittal, MBA (2024-26) ABV-IIITM, Gwalior
B14: TABLE OF CONTENTS
B15: 1 | C15: Cover | D15: Company overview & workbook guide
B16: 2 | C16: Income Statement | D16: 5-year Statement of Profit & Loss
B17: 3 | C17: Balance Sheet | D17: 5-year Statement of Assets & Liabilities
B18: 4 | C18: Cash Flow Statement | D18: 5-year Operating / Investing / Financing cash flows
B19: 5 | C19: Common Size Analysis | D19: Vertical (% of revenue / % of total assets) analysis
B20: 6 | C20: Comparative Analysis | D20: Year-on-year horizontal movement, Rs. & %
B21: 7 | C21: Ratio Analysis | D21: Liquidity, profitability, leverage & efficiency ratios
B22: 8 | C22: Trend Analysis | D22: Indexed trend of key line items (base year = 100)
B23: 9 | C23: Charts & Dashboard | D23: Visual KPI dashboard
B24: 10 | C24: Notes | D24: Assumptions, sources & definitions

Sheet Income Statement
B2: AWL AGRIBUSINESS LIMITED
B3: STATEMENT OF PROFIT & LOSS (CONSOLIDATED)
B4: Rs. in Crores, unless otherwise stated
B6: Particulars | C6: FY2021-22 | D6: FY2022-23 | E6: FY2023-24 | F6: FY2024-25 | G6: FY2025-26
B7: As At | C7: 31-Mar-22 | D7: 31-Mar-23 | E7: 31-Mar-24 | F7: 31-Mar-25 | G7: 31-Mar-26
B9: Revenue
B10: Revenue from Operations (Net Sales) | C10: 54155 | D10: 58185 | E10: 51225 | F10: 63672 | G10: 74731
B11: Total Income (Revenue from Operations) | C11: =SUM(C10:C10) -> 54155 | D11: =SUM(D10:D10) -> 58185 | E11: =SUM(E10:E10) -> 51225 | F11: =SUM(F10:F10) -> 63672 | G11: =SUM(G10:G10) -> 74731
B13: Expenses
B14: Cost of Materials Consumed | C14: 48194 | D14: 48910 | E14: 43291 | F14: 53614.4 | G14: 64185.48
B15: Purchases of Stock-in-Trade | C15: 2335 | D15: 2736.41 | E15: 1960 | F15: 3366 | G15: 2988
B16: Changes in Inventories | C16: -1757 | D16: 1239 | E16: 24 | F16: -843 | G16: -266
B17: Employee Benefit Expense | C17: 392 | D17: 394 | E17: 421 | F17: 566 | G17: 676
B18: Other Expenses | C18: 3254 | D18: 3947 | E18: 4430 | F18: 4487 | G18: 5016
B19: Total Expenses | C19: =SUM(C14:C18) -> 52418 | D19: =SUM(D14:D18) -> 57226.41 | E19: =SUM(E14:E18) -> 50126 | F19: =SUM(F14:F18) -> 61190.4 | G19: =SUM(G14:G18) -> 72599.48
B21: Operating Profit (EBITDA before Other Income) | C21: =C11-C19 -> 1737 | D21: =D11-D19 -> 958.59 | E21: =E11-E19 -> 1099 | F21: =F11-F19 -> 2481.6 | G21: =G11-G19 -> 2131.52
B22: Operating Profit Margin (%) | C22: =C21/C11 -> 0.032074601 | D22: =D21/D11 -> 0.016474865 | E22: =E21/E11 -> 0.021454368 | F22: =F21/F11 -> 0.038974746 | G22: =G21/G11 -> 0.028522568
B24: Add: Other Income | C24: 172 | D24: 961 | E24: 240 | F24: 233 | G24: 392
B25: EBITDA | C25: =C21+C24 -> 1909 | D25: =D21+D24 -> 1919.59 | E25: =E21+E24 -> 1339 | F25: =F21+F24 -> 2714.6 | G25: =G21+G24 -> 2523.52
B26: Less: Finance Costs (Interest) | C26: 541 | D26: 775 | E26: 749 | F26: 724 | G26: 707
B27: Less: Depreciation & Amortisation | C27: 309 | D27: 358 | E27: 364 | F27: 395 | G27: 449
B28: Profit Before Tax (PBT) | C28: =C25-C26-C27 -> 1059 | D28: =D25-D26-D27 -> 786.59 | E28: =E25-E26-E27 -> 226 | F28: =F25-F26-F27 -> 1595.6 | G28: =G25-G26-G27 -> 1367.52
B30: Less: Tax Expense | C30: 285.93 | D30: 237 | E30: 91.7 | F30: 432 | G30: 382.76
B31: NET PROFIT AFTER TAX (PAT) | C31: =C28-C30 -> 773.07 | D31: =D28-D30 -> 549.59 | E31: =E28-E30 -> 134.3 | F31: =F28-F30 -> 1163.6 | G31: =G28-G30 -> 984.76
B32: Net Profit Margin (%) | C32: =C31/C11 -> 0.014275136 | D32: =D31/D11 -> 0.0094455616 | E32: =E31/E11 -> 0.0026217667 | F32: =F31/F11 -> 0.018274909 | G32: =G31/G11 -> 0.013177396
B34: Weighted Avg. Shares Outstanding (Crore) | C34: 130.19 | D34: 130.29 | E34: 130.29 | F34: 130.02 | G34: 129.96
B35: Basic Earnings Per Share (Rs.) | C35: =C31/C34 -> 5.9380137 | D35: =D31/D34 -> 4.2182055 | E35: =E31/E34 -> 1.0307775 | F35: =F31/F34 -> 8.9493924 | G35: =G31/G34 -> 7.5774084
B38: Source: Consolidated Financial Statements / Annual Reports

Sheet Balance Sheet
B2: AWL AGRIBUSINESS LIMITED
B3: BALANCE SHEET (CONSOLIDATED)
B4: Rs. in Crores, as at year end
B6: Particulars | C6: FY2021-22 | D6: FY2022-23 | E6: FY2023-24 | F6: FY2024-25 | G6: FY2025-26
B7: As At | C7: 31-Mar-22 | D7: 31-Mar-23 | E7: 31-Mar-24 | F7: 31-Mar-25 | G7: 31-Mar-26
B9: EQUITY & LIABILITIES
B10: Shareholders' Funds
B11: Equity Share Capital | C11: 130 | D11: 130 | E11: 130 | F11: 130 | G11: 129
B12: Reserves & Surplus | C12: 7476 | D12: 8036 | E12: 8186 | F12: 9294 | G12: 10311
B13: Total Shareholders' Equity (Net Worth) | C13: =C11+C12 -> 7606 | D13: =D11+D12 -> 8166 | E13: =E11+E12 -> 8316 | F13: =F11+F12 -> 9424 | G13: =G11+G12 -> 10440
B15: Non-Current Liabilities
B16: Long-Term Borrowings | C16: 44.97 | D16: 0 | E16: 0 | F16: 186.24 | G16: 392.24
B17: Other Non-Current Liabilities | C17: 975 | D17: 1126.91 | E17: 1079 | F17: 1100.39 | G17: 1494
B18: Total Non-Current Liabilities | C18: =SUM(C16:C17) -> 1019.97 | D18: =SUM(D16:D17) -> 1126.91 | E18: =SUM(E16:E17) -> 1079 | F18: =SUM(F16:F17) -> 1286.63 | G18: =SUM(G16:G17) -> 1886.24
B20: Current Liabilities
B21: Short-Term Borrowings | C21: 2523 | D21: 2225 | E21: 2415 | F21: 1525.59 | G21: 425.93
B22: Trade Payables | C22: 1840 | D22: 2678 | E22: 2818 | F22: 2955.71 | G22: 3269
B23: Other Current Liabilities & Provisions | C23: 8328 | D23: 6784 | E23: 5177 | F23: 7245.96 | G23: 8733.37
B24: Total Current Liabilities | C24: =SUM(C21:C23) -> 12691 | D24: =SUM(D21:D23) -> 11687 | E24: =SUM(E21:E23) -> 10410 | F24: =SUM(F21:F23) -> 11727.26 | G24: =SUM(G21:G23) -> 12428.3
B26: TOTAL EQUITY & LIABILITIES | C26: =C13+C18+C24 -> 21316.97 | D26: =D13+D18+D24 -> 20979.91 | E26: =E13+E18+E24 -> 19805 | F26: =F13+F18+F24 -> 22437.89 | G26: =G13+G18+G24 -> 24754.54
B28: ASSETS
B29: Non-Current Assets
B30: Property, Plant & Equipment | C30: 4288 | D30: 4334 | E30: 4455 | F30: 4993.37 | G30: 5992.37
B31: Other Non-Current Assets | C31: 1647 | D31: 2115 | E31: 2633.2 | F31: 2829.13 | G31: 3106.48
B32: Total Non-Current Assets | C32: =SUM(C30:C31) -> 5935 | D32: =SUM(D30:D31) -> 6449 | E32: =SUM(E30:E31) -> 7088.2 | F32: =SUM(F30:F31) -> 7822.5 | G32: =SUM(G30:G31) -> 9098.85
B34: Current Assets
B35: Inventories | C35: 7716 | D35: 7681 | E35: 7203 | F35: 8641.28 | G35: 8190.72
B36: Trade Receivables | C36: 2218 | D36: 1931 | E36: 1782 | F36: 2415.55 | G36: 2624.32
B37: Cash & Cash Equivalents | C37: 127 | D37: 394 | E37: 258 | F37: 543 | G37: 1677
B38: Other Current Assets | C38: 5321 | D38: 4525 | E38: 3474 | F38: 3015.69 | G38: 3163.68
B39: Total Current Assets | C39: =SUM(C35:C38) -> 15382 | D39: =SUM(D35:D38) -> 14531 | E39: =SUM(E35:E38) -> 12717 | F39: =SUM(F35:F38) -> 14615.52 | G39: =SUM(G35:G38) -> 15655.72
B41: TOTAL ASSETS | C41: =C32+C39 -> 21317 | D41: =D32+D39 -> 20980 | E41: =E32+E39 -> 19805.2 | F41: =F32+F39 -> 22438.02 | G41: =G32+G39 -> 24754.57
B42: Balance Check (Total Assets − Total Equity & Liabilities) | C42: =C41-C26 -> 0.03 | D42: =D41-D26 -> 0.09 | E42: =E41-E26 -> 0.2 | F42: =F41-F26 -> 0.13 | G42: =G41-G26 -> 0.03
B44: Source: Consolidated Financial Statements / Annual Reports

Sheet Cash Flow Statement
B2: AWL AGRIBUSINESS LIMITED
B3: CASH FLOW STATEMENT (CONSOLIDATED)
B4: Rs. in Crores
B6: Particulars | C6: FY2021-22 | D6: FY2022-23 | E6: FY2023-24 | F6: FY2024-25 | G6: FY2025-26
B7: Year Ended | C7: 31-Mar-22 | D7: 31-Mar-23 | E7: 31-Mar-24 | F7: 31-Mar-25 | G7: 31-Mar-26
B9: Net Cash Flow from Operating Activities | C9: 1198 | D9: 663 | E9: 289 | F9: 2150 | G9: 3928
B10: Net Cash Flow from Investing Activities | C10: -3786 | D10: 524 | E10: 138 | F10: -278 | G10: -1096
B11: Net Cash Flow from Financing Activities | C11: 2658 | D11: -919 | E11: -847 | F11: -1544 | G11: -1678
B13: Net Increase / (Decrease) in Cash | C13: =C9+C10+C11 -> 70 | D13: =D9+D10+D11 -> 268 | E13: =E9+E10+E11 -> -420 | F13: =F9+F10+F11 -> 328 | G13: =G9+G10+G11 -> 1154
B15: Free Cash Flow (CFO less Capex) | C15: 663 | D15: -11 | E15: -641 | F15: 1190 | G15: 3104
B16: CFO / Operating Profit (%) | C16: =C9/'Income Statement'!C21 -> 0.68969488 | D16: =D9/'Income Statement'!D21 -> 0.69164085 | E16: =E9/'Income Statement'!E21 -> 0.26296633 | F16: =F9/'Income Statement'!F21 -> 0.86637653 | G16: =G9/'Income Statement'!G21 -> 1.8428164
B18: Source: Consolidated Financial Statements, AWL Agri Business Limited (FY22-26)

Sheet Common Size Analysis
B2: AWL AGRIBUSINESS LIMITED
B3: COMMON SIZE (VERTICAL) ANALYSIS
B4: Income Statement items as % of Total Revenue; Balance Sheet items as % of Total Assets
B6: Particulars | C6: FY2021-22 | D6: FY2022-23 | E6: FY2023-24 | F6: FY2024-25 | G6: FY2025-26
B8: INCOME STATEMENT — % of Total Revenue
B9: Revenue from Operations | C9: =IFERROR('Income Statement'!C10/'Income Statement'!C11,0) -> 1 | D9: =IFERROR('Income Statement'!D10/'Income Statement'!D11,0) -> 1 | E9: =IFERROR('Income Statement'!E10/'Income Statement'!E11,0) -> 1 | F9: =IFERROR('Income Statement'!F10/'Income Statement'!F11,0) -> 1 | G9: =IFERROR('Income Statement'!G10/'Income Statement'!G11,0) -> 1
B10: Cost of Materials Consumed | C10: =IFERROR('Income Statement'!C14/'Income Statement'!C11,0) -> 0.88992706 | D10: =IFERROR('Income Statement'!D14/'Income Statement'!D11,0) -> 0.84059465 | E10: =IFERROR('Income Statement'!E14/'Income Statement'!E11,0) -> 0.84511469 | F10: =IFERROR('Income Statement'!F14/'Income Statement'!F11,0) -> 0.84204046 | G10: =IFERROR('Income Statement'!G14/'Income Statement'!G11,0) -> 0.85888694
B11: Purchases of Stock-in-Trade | C11: =IFERROR('Income Statement'!C15/'Income Statement'!C11,0) -> 0.043116979 | D11: =IFERROR('Income Statement'!D15/'Income Statement'!D11,0) -> 0.047029475 | E11: =IFERROR('Income Statement'!E15/'Income Statement'!E11,0) -> 0.038262567 | F11: =IFERROR('Income Statement'!F15/'Income Statement'!F11,0) -> 0.052864681 | G11: =IFERROR('Income Statement'!G15/'Income Statement'!G11,0) -> 0.039983407
B12: Changes in Inventories | C12: =IFERROR('Income Statement'!C16/'Income Statement'!C11,0) -> -0.032443911 | D12: =IFERROR('Income Statement'!D16/'Income Statement'!D11,0) -> 0.021294148 | E12: =IFERROR('Income Statement'!E16/'Income Statement'!E11,0) -> 0.00046852123 | F12: =IFERROR('Income Statement'!F16/'Income Statement'!F11,0) -> -0.013239729 | G12: =IFERROR('Income Statement'!G16/'Income Statement'!G11,0) -> -0.0035594332
B13: Employee Benefit Expense | C13: =IFERROR('Income Statement'!C17/'Income Statement'!C11,0) -> 0.0072384821 | D13: =IFERROR('Income Statement'!D17/'Income Statement'!D11,0) -> 0.0067715047 | E13: =IFERROR('Income Statement'!E17/'Income Statement'!E11,0) -> 0.0082186432 | F13: =IFERROR('Income Statement'!F17/'Income Statement'!F11,0) -> 0.0088893077 | G13: =IFERROR('Income Statement'!G17/'Income Statement'!G11,0) -> 0.0090457775
B14: Other Expenses | C14: =IFERROR('Income Statement'!C18/'Income Statement'!C11,0) -> 0.060086788 | D14: =IFERROR('Income Statement'!D18/'Income Statement'!D11,0) -> 0.067835353 | E14: =IFERROR('Income Statement'!E18/'Income Statement'!E11,0) -> 0.08648121 | F14: =IFERROR('Income Statement'!F18/'Income Statement'!F11,0) -> 0.070470536 | G14: =IFERROR('Income Statement'!G18/'Income Statement'!G11,0) -> 0.06712074
B15: Total Expenses | C15: =IFERROR('Income Statement'!C19/'Income Statement'!C11,0) -> 0.9679254 | D15: =IFERROR('Income Statement'!D19/'Income Statement'!D11,0) -> 0.98352514 | E15: =IFERROR('Income Statement'!E19/'Income Statement'!E11,0) -> 0.97854563 | F15: =IFERROR('Income Statement'!F19/'Income Statement'!F11,0) -> 0.96102525 | G15: =IFERROR('Income Statement'!G19/'Income Statement'!G11,0) -> 0.97147743
B16: Operating Profit | C16: =IFERROR('Income Statement'!C21/'Income Statement'!C11,0) -> 0.032074601 | D16: =IFERROR('Income Statement'!D21/'Income Statement'!D11,0) -> 0.016474865 | E16: =IFERROR('Income Statement'!E21/'Income Statement'!E11,0) -> 0.021454368 | F16: =IFERROR('Income Statement'!F21/'Income Statement'!F11,0) -> 0.038974746 | G16: =IFERROR('Income Statement'!G21/'Income Statement'!G11,0) -> 0.028522568
B17: Other Income | C17: =IFERROR('Income Statement'!C24/'Income Statement'!C11,0) -> 0.0031760687 | D17: =IFERROR('Income Statement'!D24/'Income Statement'!D11,0) -> 0.016516284 | E17: =IFERROR('Income Statement'!E24/'Income Statement'!E11,0) -> 0.0046852123 | F17: =IFERROR('Income Statement'!F24/'Income Statement'!F11,0) -> 0.0036593793 | G17: =IFERROR('Income Statement'!G24/'Income Statement'!G11,0) -> 0.0052454805
B18: EBITDA | C18: =IFERROR('Income Statement'!C25/'Income Statement'!C11,0) -> 0.035250669 | D18: =IFERROR('Income Statement'!D25/'Income Statement'!D11,0) -> 0.032991149 | E18: =IFERROR('Income Statement'!E25/'Income Statement'!E11,0) -> 0.02613958 | F18: =IFERROR('Income Statement'!F25/'Income Statement'!F11,0) -> 0.042634125 | G18: =IFERROR('Income Statement'!G25/'Income Statement'!G11,0) -> 0.033768048
B19: Finance Costs | C19: =IFERROR('Income Statement'!C26/'Income Statement'!C11,0) -> 0.009989844 | D19: =IFERROR('Income Statement'!D26/'Income Statement'!D11,0) -> 0.013319584 | E19: =IFERROR('Income Statement'!E26/'Income Statement'!E11,0) -> 0.014621767 | F19: =IFERROR('Income Statement'!F26/'Income Statement'!F11,0) -> 0.011370775 | G19: =IFERROR('Income Statement'!G26/'Income Statement'!G11,0) -> 0.0094605987
B20: Depreciation & Amortisation | C20: =IFERROR('Income Statement'!C27/'Income Statement'!C11,0) -> 0.0057058443 | D20: =IFERROR('Income Statement'!D27/'Income Statement'!D11,0) -> 0.0061527885 | E20: =IFERROR('Income Statement'!E27/'Income Statement'!E11,0) -> 0.0071059053 | F20: =IFERROR('Income Statement'!F27/'Income Statement'!F11,0) -> 0.0062036688 | G20: =IFERROR('Income Statement'!G27/'Income Statement'!G11,0) -> 0.0060082161
B21: Profit Before Tax | C21: =IFERROR('Income Statement'!C28/'Income Statement'!C11,0) -> 0.019554981 | D21: =IFERROR('Income Statement'!D28/'Income Statement'!D11,0) -> 0.013518776 | E21: =IFERROR('Income Statement'!E28/'Income Statement'!E11,0) -> 0.0044119082 | F21: =IFERROR('Income Statement'!F28/'Income Statement'!F11,0) -> 0.025059681 | G21: =IFERROR('Income Statement'!G28/'Income Statement'!G11,0) -> 0.018299233
B22: Tax Expense | C22: =IFERROR('Income Statement'!C30/'Income Statement'!C11,0) -> 0.0052798449 | D22: =IFERROR('Income Statement'!D30/'Income Statement'!D11,0) -> 0.0040732147 | E22: =IFERROR('Income Statement'!E30/'Income Statement'!E11,0) -> 0.0017901415 | F22: =IFERROR('Income Statement'!F30/'Income Statement'!F11,0) -> 0.006784772 | G22: =IFERROR('Income Statement'!G30/'Income Statement'!G11,0) -> 0.005121837
B23: Net Profit After Tax | C23: =IFERROR('Income Statement'!C31/'Income Statement'!C11,0) -> 0.014275136 | D23: =IFERROR('Income Statement'!D31/'Income Statement'!D11,0) -> 0.0094455616 | E23: =IFERROR('Income Statement'!E31/'Income Statement'!E11,0) -> 0.0026217667 | F23: =IFERROR('Income Statement'!F31/'Income Statement'!F11,0) -> 0.018274909 | G23: =IFERROR('Income Statement'!G31/'Income Statement'!G11,0) -> 0.013177396
B25: BALANCE SHEET — % of Total Assets
B26: Equity Share Capital | C26: =IFERROR('Balance Sheet'!C11/'Balance Sheet'!C41,0) -> 0.0060984191 | D26: =IFERROR('Balance Sheet'!D11/'Balance Sheet'!D41,0) -> 0.0061963775 | E26: =IFERROR('Balance Sheet'!E11/'Balance Sheet'!E41,0) -> 0.0065639327 | F26: =IFERROR('Balance Sheet'!F11/'Balance Sheet'!F41,0) -> 0.0057937376 | G26: =IFERROR('Balance Sheet'!G11/'Balance Sheet'!G41,0) -> 0.005211159
B27: Reserves & Surplus | C27: =IFERROR('Balance Sheet'!C12/'Balance Sheet'!C41,0) -> 0.35070601 | D27: =IFERROR('Balance Sheet'!D12/'Balance Sheet'!D41,0) -> 0.38303146 | E27: =IFERROR('Balance Sheet'!E12/'Balance Sheet'!E41,0) -> 0.41332579 | F27: =IFERROR('Balance Sheet'!F12/'Balance Sheet'!F41,0) -> 0.41420767 | G27: =IFERROR('Balance Sheet'!G12/'Balance Sheet'!G41,0) -> 0.41652915
B28: Total Shareholders' Equity | C28: =IFERROR('Balance Sheet'!C13/'Balance Sheet'!C41,0) -> 0.35680443 | D28: =IFERROR('Balance Sheet'!D13/'Balance Sheet'!D41,0) -> 0.38922784 | E28: =IFERROR('Balance Sheet'!E13/'Balance Sheet'!E41,0) -> 0.41988973 | F28: =IFERROR('Balance Sheet'!F13/'Balance Sheet'!F41,0) -> 0.42000141 | G28: =IFERROR('Balance Sheet'!G13/'Balance Sheet'!G41,0) -> 0.42174031
B29: Long-Term Borrowings | C29: =IFERROR('Balance Sheet'!C16/'Balance Sheet'!C41,0) -> 0.0021095839 | D29: =IFERROR('Balance Sheet'!D16/'Balance Sheet'!D41,0) -> 0 | E29: =IFERROR('Balance Sheet'!E16/'Balance Sheet'!E41,0) -> 0 | F29: =IFERROR('Balance Sheet'!F16/'Balance Sheet'!F41,0) -> 0.0083001976 | G29: =IFERROR('Balance Sheet'!G16/'Balance Sheet'!G41,0) -> 0.015845155
B30: Total Non-Current Liabilities | C30: =IFERROR('Balance Sheet'!C18/'Balance Sheet'!C41,0) -> 0.047847727 | D30: =IFERROR('Balance Sheet'!D18/'Balance Sheet'!D41,0) -> 0.053713537 | E30: =IFERROR('Balance Sheet'!E18/'Balance Sheet'!E41,0) -> 0.054480641 | F30: =IFERROR('Balance Sheet'!F18/'Balance Sheet'!F41,0) -> 0.057341512 | G30: =IFERROR('Balance Sheet'!G18/'Balance Sheet'!G41,0) -> 0.076197648
B31: Short-Term Borrowings | C31: =IFERROR('Balance Sheet'!C21/'Balance Sheet'!C41,0) -> 0.11835624 | D31: =IFERROR('Balance Sheet'!D21/'Balance Sheet'!D41,0) -> 0.10605338 | E31: =IFERROR('Balance Sheet'!E21/'Balance Sheet'!E41,0) -> 0.12193767 | F31: =IFERROR('Balance Sheet'!F21/'Balance Sheet'!F41,0) -> 0.067991293 | G31: =IFERROR('Balance Sheet'!G21/'Balance Sheet'!G41,0) -> 0.017206116
B32: Trade Payables | C32: =IFERROR('Balance Sheet'!C22/'Balance Sheet'!C41,0) -> 0.086316086 | D32: =IFERROR('Balance Sheet'!D22/'Balance Sheet'!D41,0) -> 0.12764538 | E32: =IFERROR('Balance Sheet'!E22/'Balance Sheet'!E41,0) -> 0.14228586 | F32: =IFERROR('Balance Sheet'!F22/'Balance Sheet'!F41,0) -> 0.13172775 | G32: =IFERROR('Balance Sheet'!G22/'Balance Sheet'!G41,0) -> 0.13205642
B33: Total Current Liabilities | C33: =IFERROR('Balance Sheet'!C24/'Balance Sheet'!C41,0) -> 0.59534644 | D33: =IFERROR('Balance Sheet'!D24/'Balance Sheet'!D41,0) -> 0.55705434 | E33: =IFERROR('Balance Sheet'!E24/'Balance Sheet'!E41,0) -> 0.52561953 | F33: =IFERROR('Balance Sheet'!F24/'Balance Sheet'!F41,0) -> 0.52265129 | G33: =IFERROR('Balance Sheet'!G24/'Balance Sheet'!G41,0) -> 0.50206083
B35: Property, Plant & Equipment | C35: =IFERROR('Balance Sheet'!C30/'Balance Sheet'!C41,0) -> 0.20115401 | D35: =IFERROR('Balance Sheet'!D30/'Balance Sheet'!D41,0) -> 0.20657769 | E35: =IFERROR('Balance Sheet'!E30/'Balance Sheet'!E41,0) -> 0.22494092 | F35: =IFERROR('Balance Sheet'!F30/'Balance Sheet'!F41,0) -> 0.22254058 | G35: =IFERROR('Balance Sheet'!G30/'Balance Sheet'!G41,0) -> 0.24207126
B36: Total Non-Current Assets | C36: =IFERROR('Balance Sheet'!C32/'Balance Sheet'!C41,0) -> 0.27841629 | D36: =IFERROR('Balance Sheet'!D32/'Balance Sheet'!D41,0) -> 0.30738799 | E36: =IFERROR('Balance Sheet'!E32/'Balance Sheet'!E41,0) -> 0.35789591 | F36: =IFERROR('Balance Sheet'!F32/'Balance Sheet'!F41,0) -> 0.34862702 | G36: =IFERROR('Balance Sheet'!G32/'Balance Sheet'!G41,0) -> 0.36756243
B37: Inventories | C37: =IFERROR('Balance Sheet'!C35/'Balance Sheet'!C41,0) -> 0.36196463 | D37: =IFERROR('Balance Sheet'!D35/'Balance Sheet'!D41,0) -> 0.36611058 | E37: =IFERROR('Balance Sheet'!E35/'Balance Sheet'!E41,0) -> 0.36369236 | F37: =IFERROR('Balance Sheet'!F35/'Balance Sheet'!F41,0) -> 0.38511776 | G37: =IFERROR('Balance Sheet'!G35/'Balance Sheet'!G41,0) -> 0.33087709
B38: Trade Receivables | C38: =IFERROR('Balance Sheet'!C36/'Balance Sheet'!C41,0) -> 0.10404841 | D38: =IFERROR('Balance Sheet'!D36/'Balance Sheet'!D41,0) -> 0.092040038 | E38: =IFERROR('Balance Sheet'!E36/'Balance Sheet'!E41,0) -> 0.08997637 | F38: =IFERROR('Balance Sheet'!F36/'Balance Sheet'!F41,0) -> 0.10765433 | G38: =IFERROR('Balance Sheet'!G36/'Balance Sheet'!G41,0) -> 0.10601356
B39: Cash & Cash Equivalents | C39: =IFERROR('Balance Sheet'!C37/'Balance Sheet'!C41,0) -> 0.0059576864 | D39: =IFERROR('Balance Sheet'!D37/'Balance Sheet'!D41,0) -> 0.01877979 | E39: =IFERROR('Balance Sheet'!E37/'Balance Sheet'!E41,0) -> 0.013026882 | F39: =IFERROR('Balance Sheet'!F37/'Balance Sheet'!F41,0) -> 0.024199996 | G39: =IFERROR('Balance Sheet'!G37/'Balance Sheet'!G41,0) -> 0.067745067
B40: Total Current Assets | C40: =IFERROR('Balance Sheet'!C39/'Balance Sheet'!C41,0) -> 0.72158371 | D40: =IFERROR('Balance Sheet'!D39/'Balance Sheet'!D41,0) -> 0.69261201 | E40: =IFERROR('Balance Sheet'!E39/'Balance Sheet'!E41,0) -> 0.64210409 | F40: =IFERROR('Balance Sheet'!F39/'Balance Sheet'!F41,0) -> 0.65137298 | G40: =IFERROR('Balance Sheet'!G39/'Balance Sheet'!G41,0) -> 0.63243757
B42: Note: Ratios/analyses on this sheet are formula-linked to the Income Statement, Balance Sheet and Cash Flow Statement tabs.

Sheet Comparative Analysis
B2: AWL AGRIBUSINESS LIMITED
B3: COMPARATIVE (HORIZONTAL / YoY) ANALYSIS
B4: Rs. in Crores | Year-on-year change shown for each consecutive pair of years
B6: Particulars | C6: FY2021-22 | D6: FY2022-23 | E6: FY2023-24 | F6: FY2024-25 | G6: FY2025-26 | H6: FY22-FY23 (% Chg ) | I6: FY23-FY24 (% Chg ) | J6: FY24-FY25 (% Chg ) | K6: FY25-FY26 (% Chg )
B8: INCOME STATEMENT
B9: Revenue from Operations | C9: ='Income Statement'!C10 -> 54155 | D9: ='Income Statement'!D10 -> 58185 | E9: ='Income Statement'!E10 -> 51225 | F9: ='Income Statement'!F10 -> 63672 | G9: ='Income Statement'!G10 -> 74731 | H9: =IFERROR((D9-C9)/ABS(C9),"n/m") -> 0.074416028 | I9: =IFERROR((E9-D9)/ABS(D9),"n/m") -> -0.11961846 | J9: =IFERROR((F9-E9)/ABS(E9),"n/m") -> 0.24298682 | K9: =IFERROR((G9-F9)/ABS(F9),"n/m") -> 0.17368702
B10: Total Expenses | C10: ='Income Statement'!C19 -> 52418 | D10: ='Income Statement'!D19 -> 57226.41 | E10: ='Income Statement'!E19 -> 50126 | F10: ='Income Statement'!F19 -> 61190.4 | G10: ='Income Statement'!G19 -> 72599.48 | H10: =IFERROR((D10-C10)/ABS(C10),"n/m") -> 0.091732039 | I10: =IFERROR((E10-D10)/ABS(D10),"n/m") -> -0.12407575 | J10: =IFERROR((F10-E10)/ABS(E10),"n/m") -> 0.22073176 | K10: =IFERROR((G10-F10)/ABS(F10),"n/m") -> 0.18645212
B11: Operating Profit | C11: ='Income Statement'!C21 -> 1737 | D11: ='Income Statement'!D21 -> 958.59 | E11: ='Income Statement'!E21 -> 1099 | F11: ='Income Statement'!F21 -> 2481.6 | G11: ='Income Statement'!G21 -> 2131.52 | H11: =IFERROR((D11-C11)/ABS(C11),"n/m") -> -0.44813472 | I11: =IFERROR((E11-D11)/ABS(D11),"n/m") -> 0.14647555 | J11: =IFERROR((F11-E11)/ABS(E11),"n/m") -> 1.2580528 | K11: =IFERROR((G11-F11)/ABS(F11),"n/m") -> -0.14107028
B12: EBITDA | C12: ='Income Statement'!C25 -> 1909 | D12: ='Income Statement'!D25 -> 1919.59 | E12: ='Income Statement'!E25 -> 1339 | F12: ='Income Statement'!F25 -> 2714.6 | G12: ='Income Statement'!G25 -> 2523.52 | H12: =IFERROR((D12-C12)/ABS(C12),"n/m") -> 0.005547407 | I12: =IFERROR((E12-D12)/ABS(D12),"n/m") -> -0.30245521 | J12: =IFERROR((F12-E12)/ABS(E12),"n/m") -> 1.0273338 | K12: =IFERROR((G12-F12)/ABS(F12),"n/m") -> -0.070389744
B13: Profit Before Tax | C13: ='Income Statement'!C28 -> 1059 | D13: ='Income Statement'!D28 -> 786.59 | E13: ='Income Statement'!E28 -> 226 | F13: ='Income Statement'!F28 -> 1595.6 | G13: ='Income Statement'!G28 -> 1367.52 | H13: =IFERROR((D13-C13)/ABS(C13),"n/m") -> -0.25723324 | I13: =IFERROR((E13-D13)/ABS(D13),"n/m") -> -0.71268386 | J13: =IFERROR((F13-E13)/ABS(E13),"n/m") -> 6.060177 | K13: =IFERROR((G13-F13)/ABS(F13),"n/m") -> -0.14294309
B14: Net Profit After Tax | C14: ='Income Statement'!C31 -> 773.07 | D14: ='Income Statement'!D31 -> 549.59 | E14: ='Income Statement'!E31 -> 134.3 | F14: ='Income Statement'!F31 -> 1163.6 | G14: ='Income Statement'!G31 -> 984.76 | H14: =IFERROR((D14-C14)/ABS(C14),"n/m") -> -0.2890812 | I14: =IFERROR((E14-D14)/ABS(D14),"n/m") -> -0.75563602 | J14: =IFERROR((F14-E14)/ABS(E14),"n/m") -> 7.6641847 | K14: =IFERROR((G14-F14)/ABS(F14),"n/m") -> -0.15369543
B15: Basic EPS (Rs.) | C15: ='Income Statement'!C35 -> 5.9380137 | D15: ='Income Statement'!D35 -> 4.2182055 | E15: ='Income Statement'!E35 -> 1.0307775 | F15: ='Income Statement'!F35 -> 8.9493924 | G15: ='Income Statement'!G35 -> 7.5774084 | H15: =IFERROR((D15-C15)/ABS(C15),"n/m") -> -0.28962684 | I15: =IFERROR((E15-D15)/ABS(D15),"n/m") -> -0.75563602 | J15: =IFERROR((F15-E15)/ABS(E15),"n/m") -> 7.6821767 | K15: =IFERROR((G15-F15)/ABS(F15),"n/m") -> -0.15330471
B17: BALANCE SHEET
B18: Total Shareholders' Equity | C18: ='Balance Sheet'!C13 -> 7606 | D18: ='Balance Sheet'!D13 -> 8166 | E18: ='Balance Sheet'!E13 -> 8316 | F18: ='Balance Sheet'!F13 -> 9424 | G18: ='Balance Sheet'!G13 -> 10440 | H18: =IFERROR((D18-C18)/ABS(C18),"n/m") -> 0.073626085 | I18: =IFERROR((E18-D18)/ABS(D18),"n/m") -> 0.018368846 | J18: =IFERROR((F18-E18)/ABS(E18),"n/m") -> 0.13323713 | K18: =IFERROR((G18-F18)/ABS(F18),"n/m") -> 0.10780985
B19: Total Borrowings (LT + ST) | C19: ='Balance Sheet'!C16+'Balance Sheet'!C21 -> 2567.97 | D19: ='Balance Sheet'!D16+'Balance Sheet'!D21 -> 2225 | E19: ='Balance Sheet'!E16+'Balance Sheet'!E21 -> 2415 | F19: ='Balance Sheet'!F16+'Balance Sheet'!F21 -> 1711.83 | G19: ='Balance Sheet'!G16+'Balance Sheet'!G21 -> 818.17 | H19: =IFERROR((D19-C19)/ABS(C19),"n/m") -> -0.13355686 | I19: =IFERROR((E19-D19)/ABS(D19),"n/m") -> 0.085393258 | J19: =IFERROR((F19-E19)/ABS(E19),"n/m") -> -0.2911677 | K19: =IFERROR((G19-F19)/ABS(F19),"n/m") -> -0.5220495
B20: Total Assets | C20: ='Balance Sheet'!C41 -> 21317 | D20: ='Balance Sheet'!D41 -> 20980 | E20: ='Balance Sheet'!E41 -> 19805.2 | F20: ='Balance Sheet'!F41 -> 22438.02 | G20: ='Balance Sheet'!G41 -> 24754.57 | H20: =IFERROR((D20-C20)/ABS(C20),"n/m") -> -0.015808979 | I20: =IFERROR((E20-D20)/ABS(D20),"n/m") -> -0.055996187 | J20: =IFERROR((F20-E20)/ABS(E20),"n/m") -> 0.13293579 | K20: =IFERROR((G20-F20)/ABS(F20),"n/m") -> 0.10324218
B21: Trade Receivables | C21: ='Balance Sheet'!C36 -> 2218 | D21: ='Balance Sheet'!D36 -> 1931 | E21: ='Balance Sheet'!E36 -> 1782 | F21: ='Balance Sheet'!F36 -> 2415.55 | G21: ='Balance Sheet'!G36 -> 2624.32 | H21: =IFERROR((D21-C21)/ABS(C21),"n/m") -> -0.12939585 | I21: =IFERROR((E21-D21)/ABS(D21),"n/m") -> -0.077162092 | J21: =IFERROR((F21-E21)/ABS(E21),"n/m") -> 0.3555275 | K21: =IFERROR((G21-F21)/ABS(F21),"n/m") -> 0.086427522
B22: Inventories | C22: ='Balance Sheet'!C35 -> 7716 | D22: ='Balance Sheet'!D35 -> 7681 | E22: ='Balance Sheet'!E35 -> 7203 | F22: ='Balance Sheet'!F35 -> 8641.28 | G22: ='Balance Sheet'!G35 -> 8190.72 | H22: =IFERROR((D22-C22)/ABS(C22),"n/m") -> -0.004536029 | I22: =IFERROR((E22-D22)/ABS(D22),"n/m") -> -0.06223148 | J22: =IFERROR((F22-E22)/ABS(E22),"n/m") -> 0.19967791 | K22: =IFERROR((G22-F22)/ABS(F22),"n/m") -> -0.052140424
B24: CASH FLOW
B25: Cash Flow from Operations | C25: ='Cash Flow Statement'!C9 -> 1198 | D25: ='Cash Flow Statement'!D9 -> 663 | E25: ='Cash Flow Statement'!E9 -> 289 | F25: ='Cash Flow Statement'!F9 -> 2150 | G25: ='Cash Flow Statement'!G9 -> 3928 | H25: =IFERROR((D25-C25)/ABS(C25),"n/m") -> -0.44657763 | I25: =IFERROR((E25-D25)/ABS(D25),"n/m") -> -0.56410256 | J25: =IFERROR((F25-E25)/ABS(E25),"n/m") -> 6.4394464 | K25: =IFERROR((G25-F25)/ABS(F25),"n/m") -> 0.82697674
B26: Free Cash Flow | C26: ='Cash Flow Statement'!C15 -> 663 | D26: ='Cash Flow Statement'!D15 -> -11 | E26: ='Cash Flow Statement'!E15 -> -641 | F26: ='Cash Flow Statement'!F15 -> 1190 | G26: ='Cash Flow Statement'!G15 -> 3104 | H26: =IFERROR((D26-C26)/ABS(C26),"n/m") -> -1.0165913 | I26: =IFERROR((E26-D26)/ABS(D26),"n/m") -> -57.272727 | J26: =IFERROR((F26-E26)/ABS(E26),"n/m") -> 2.8564743 | K26: =IFERROR((G26-F26)/ABS(F26),"n/m") -> 1.6084034
B28: Positive percentages indicate growth over the prior year; negative percentages (shown in brackets) indicate a decline.

Sheet Ratio Analysis
B2: AWL AGRIBUSINESS LIMITED
B3: RATIO ANALYSIS
B4: Liquidity, Profitability, Leverage, Efficiency & Market Ratios
B6: Ratio | C6: Formula | D6: FY2021-22 | E6: FY2022-23 | F6: FY2023-24 | G6: FY2024-25 | H6: FY2025-26
B8: A. LIQUIDITY RATIOS
B9: Current Ratio | C9: Current Assets/ Current Liabilities | D9: ='Balance Sheet'!C39/'Balance Sheet'!C24 -> 1.21204 | E9: ='Balance Sheet'!D39/'Balance Sheet'!D24 -> 1.2433473 | F9: ='Balance Sheet'!E39/'Balance Sheet'!E24 -> 1.2216138 | G9: ='Balance Sheet'!F39/'Balance Sheet'!F24 -> 1.246286 | H9: ='Balance Sheet'!G39/'Balance Sheet'!G24 -> 1.2596831
B10: Quick Ratio | C10: (Curr. Assets − Inventories) / Current Liabilities | D10: =('Balance Sheet'!C39-'Balance Sheet'!C35)/'Balance Sheet'!C24 -> 0.60405011 | E10: =('Balance Sheet'!D39-'Balance Sheet'!D35)/'Balance Sheet'!D24 -> 0.58612133 | F10: =('Balance Sheet'!E39-'Balance Sheet'!E35)/'Balance Sheet'!E24 -> 0.529683 | G10: =('Balance Sheet'!F39-'Balance Sheet'!F35)/'Balance Sheet'!F24 -> 0.50943187 | H10: =('Balance Sheet'!G39-'Balance Sheet'!G35)/'Balance Sheet'!G24 -> 0.6006453
B11: Cash Ratio | C11: Cash & Equivalents / Current Liabilities | D11: ='Balance Sheet'!C37/'Balance Sheet'!C24 -> 0.010007092 | E11: ='Balance Sheet'!D37/'Balance Sheet'!D24 -> 0.033712672 | F11: ='Balance Sheet'!E37/'Balance Sheet'!E24 -> 0.024783862 | G11: ='Balance Sheet'!F37/'Balance Sheet'!F24 -> 0.046302376 | H11: ='Balance Sheet'!G37/'Balance Sheet'!G24 -> 0.13493398
B12: Working Capital (Rs In Crore) | C12: Current Assets - Current Liabilities | D12: ='Balance Sheet'!C39-'Balance Sheet'!C24 -> 2691 | E12: ='Balance Sheet'!D39-'Balance Sheet'!D24 -> 2844 | F12: ='Balance Sheet'!E39-'Balance Sheet'!E24 -> 2307 | G12: ='Balance Sheet'!F39-'Balance Sheet'!F24 -> 2888.26 | H12: ='Balance Sheet'!G39-'Balance Sheet'!G24 -> 3227.42
B14: B. PROFITABILITY RATIOS
B15: Gross Profit Margin | C15: (Revenue − COGS) / Revenue | D15: =('Income Statement'!C11-('Income Statement'!C14+'Income Statement'!C15+'Income Statement'!C16))/'Income Statement'!C11 -> 0.099399871 | E15: =('Income Statement'!D11-('Income Statement'!D14+'Income Statement'!D15+'Income Statement'!D16))/'Income Statement'!D11 -> 0.091081722 | F15: =('Income Statement'!E11-('Income Statement'!E14+'Income Statement'!E15+'Income Statement'!E16))/'Income Statement'!E11 -> 0.11615422 | G15: =('Income Statement'!F11-('Income Statement'!F14+'Income Statement'!F15+'Income Statement'!F16))/'Income Statement'!F11 -> 0.11833459 | H15: =('Income Statement'!G11-('Income Statement'!G14+'Income Statement'!G15+'Income Statement'!G16))/'Income Statement'!G11 -> 0.10468908
B16: Operating Profit Margin | C16: Operating Profit / Total Operating Revenue | D16: ='Income Statement'!C21/'Income Statement'!C11 -> 0.032074601 | E16: ='Income Statement'!D21/'Income Statement'!D11 -> 0.016474865 | F16: ='Income Statement'!E21/'Income Statement'!E11 -> 0.021454368 | G16: ='Income Statement'!F21/'Income Statement'!F11 -> 0.038974746 | H16: ='Income Statement'!G21/'Income Statement'!G11 -> 0.028522568
B17: EBITDA Margin | C17: EBITDA / Total Operating Revenue | D17: ='Income Statement'!C25/'Income Statement'!C11 -> 0.035250669 | E17: ='Income Statement'!D25/'Income Statement'!D11 -> 0.032991149 | F17: ='Income Statement'!E25/'Income Statement'!E11 -> 0.02613958 | G17: ='Income Statement'!F25/'Income Statement'!F11 -> 0.042634125 | H17: ='Income Statement'!G25/'Income Statement'!G11 -> 0.033768048
B18: Net Profit Margin | C18: Profit After Tax / Total Operating Revenue | D18: ='Income Statement'!C31/'Income Statement'!C11 -> 0.014275136 | E18: ='Income Statement'!D31/'Income Statement'!D11 -> 0.0094455616 | F18: ='Income Statement'!E31/'Income Statement'!E11 -> 0.0026217667 | G18: ='Income Statement'!F31/'Income Statement'!F11 -> 0.018274909 | H18: ='Income Statement'!G31/'Income Statement'!G11 -> 0.013177396
B19: Return on Equity (ROE) | C19: Profit After Tax / Total Shareholder's Equity | D19: ='Income Statement'!C31/'Balance Sheet'!C13 -> 0.1016395 | E19: ='Income Statement'!D31/'Balance Sheet'!D13 -> 0.067302229 | F19: ='Income Statement'!E31/'Balance Sheet'!E13 -> 0.016149591 | G19: ='Income Statement'!F31/'Balance Sheet'!F13 -> 0.12347199 | H19: ='Income Statement'!G31/'Balance Sheet'!G13 -> 0.09432567
B20: Return on Assets (ROA) | C20: Profit After Tax / Total Assets | D20: ='Income Statement'!C31/'Balance Sheet'!C41 -> 0.036265422 | E20: ='Income Statement'!D31/'Balance Sheet'!D41 -> 0.026195901 | F20: ='Income Statement'!E31/'Balance Sheet'!E41 -> 0.0067810474 | G20: ='Income Statement'!F31/'Balance Sheet'!F41 -> 0.051858408 | H20: ='Income Statement'!G31/'Balance Sheet'!G41 -> 0.039780937
B21: Return on Capital Employed (ROCE) | C21: Operating Profit / (Total Assets - Current Liabilities) | D21: ='Income Statement'!C21/('Balance Sheet'!C41-'Balance Sheet'!C24) -> 0.20136796 | E21: ='Income Statement'!D21/('Balance Sheet'!D41-'Balance Sheet'!D24) -> 0.10315183 | F21: ='Income Statement'!E21/('Balance Sheet'!E41-'Balance Sheet'!E24) -> 0.11697463 | G21: ='Income Statement'!F21/('Balance Sheet'!F41-'Balance Sheet'!F24) -> 0.23169224 | H21: ='Income Statement'!G21/('Balance Sheet'!G41-'Balance Sheet'!G24) -> 0.17292498
B23: C. LEVERAGE / SOLVENCY RATIOS
B24: Debt-to-Equity Ratio | C24: Total Borrowings / Net Worth | D24: =('Balance Sheet'!C16+'Balance Sheet'!C21)/'Balance Sheet'!C13 -> 0.33762424 | E24: =('Balance Sheet'!D16+'Balance Sheet'!D21)/'Balance Sheet'!D13 -> 0.27247122 | F24: =('Balance Sheet'!E16+'Balance Sheet'!E21)/'Balance Sheet'!E13 -> 0.29040404 | G24: =('Balance Sheet'!F16+'Balance Sheet'!F21)/'Balance Sheet'!F13 -> 0.1816458 | H24: =('Balance Sheet'!G16+'Balance Sheet'!G21)/'Balance Sheet'!G13 -> 0.078368774
B25: Debt-to-Total-Assets | C25: Total Debt / Total Assets | D25: =('Balance Sheet'!C16+'Balance Sheet'!C21)/'Balance Sheet'!C41 -> 0.12046583 | E25: =('Balance Sheet'!D16+'Balance Sheet'!D21)/'Balance Sheet'!D41 -> 0.10605338 | F25: =('Balance Sheet'!E16+'Balance Sheet'!E21)/'Balance Sheet'!E41 -> 0.12193767 | G25: =('Balance Sheet'!F16+'Balance Sheet'!F21)/'Balance Sheet'!F41 -> 0.076291491 | H25: =('Balance Sheet'!G16+'Balance Sheet'!G21)/'Balance Sheet'!G41 -> 0.033051271
B26: Interest Coverage Ratio | C26: EBITDA / Interest | D26: ='Income Statement'!C25/'Income Statement'!C26 -> 3.5286506 | E26: ='Income Statement'!D25/'Income Statement'!D26 -> 2.4768903 | F26: ='Income Statement'!E25/'Income Statement'!E26 -> 1.787717 | G26: ='Income Statement'!F25/'Income Statement'!F26 -> 3.7494475 | H26: ='Income Statement'!G25/'Income Statement'!G26 -> 3.5693352
B27: Equity Multiplier | C27: Total Assets / Net Worth | D27: ='Balance Sheet'!C41/'Balance Sheet'!C13 -> 2.8026558 | E27: ='Balance Sheet'!D41/'Balance Sheet'!D13 -> 2.5691893 | F27: ='Balance Sheet'!E41/'Balance Sheet'!E13 -> 2.3815777 | G27: ='Balance Sheet'!F41/'Balance Sheet'!F13 -> 2.3809444 | H27: ='Balance Sheet'!G41/'Balance Sheet'!G13 -> 2.3711274
B29: D. EFFICIENCY / ACTIVITY RATIOS
B30: Asset Turnover Ratio | C30: Total Revenue / Total Assets | D30: ='Income Statement'!C11/'Balance Sheet'!C41 -> 2.5404607 | E30: ='Income Statement'!D11/'Balance Sheet'!D41 -> 2.7733556 | F30: ='Income Statement'!E11/'Balance Sheet'!E41 -> 2.5864419 | G30: ='Income Statement'!F11/'Balance Sheet'!F41 -> 2.8376835 | H30: ='Income Statement'!G11/'Balance Sheet'!G41 -> 3.0188769
B31: Days Sales Outstanding (DSO) | C31: Average Receivables / Total Revenue × 365 | D31: ='Balance Sheet'!C36/'Income Statement'!C11*365 -> 14.949128 | E31: ='Balance Sheet'!D36/'Income Statement'!D11*365 -> 12.113345 | F31: ='Balance Sheet'!E36/'Income Statement'!E11*365 -> 12.697511 | G31: ='Balance Sheet'!F36/'Income Statement'!F11*365 -> 13.84715 | H31: ='Balance Sheet'!G36/'Income Statement'!G11*365 -> 12.817663
B32: Days Inventory Outstanding (DIO) | C32: Average Inventories / COGS × 365 | D32: ='Balance Sheet'!C35/('Income Statement'!C14+'Income Statement'!C15+'Income Statement'!C16)*365 -> 57.745018 | E32: ='Balance Sheet'!D35/('Income Statement'!D14+'Income Statement'!D15+'Income Statement'!D16)*365 -> 53.012069 | F32: ='Balance Sheet'!E35/('Income Statement'!E14+'Income Statement'!E15+'Income Statement'!E16)*365 -> 58.069464 | G32: ='Balance Sheet'!F35/('Income Statement'!F14+'Income Statement'!F15+'Income Statement'!F16)*365 -> 56.184775 | H32: ='Balance Sheet'!G35/('Income Statement'!G14+'Income Statement'!G15+'Income Statement'!G16)*365 -> 44.682789
B33: Days Payables Outstanding (DPO) | C33: Average Trade Payables / COGS × 365 | D33: ='Balance Sheet'!C22/('Income Statement'!C14+'Income Statement'!C15+'Income Statement'!C16)*365 -> 13.770196 | E33: ='Balance Sheet'!D22/('Income Statement'!D14+'Income Statement'!D15+'Income Statement'!D16)*365 -> 18.482791 | F33: ='Balance Sheet'!E22/('Income Statement'!E14+'Income Statement'!E15+'Income Statement'!E16)*365 -> 22.718277 | G33: ='Balance Sheet'!F22/('Income Statement'!F14+'Income Statement'!F15+'Income Statement'!F16)*365 -> 19.217743 | H33: ='Balance Sheet'!G22/('Income Statement'!G14+'Income Statement'!G15+'Income Statement'!G16)*365 -> 17.833357
B34: Cash Conversion Cycle | C34: DIO + DSO - DPO | D34: =D31+D32-D33 -> 58.923949 | E34: =E31+E32-E33 -> 46.642623 | F34: =F31+F32-F33 -> 48.048698 | G34: =G31+G32-G33 -> 50.814182 | H34: =H31+H32-H33 -> 39.667095
B35: Fixed Asset Turnover | C35: Revenue / PP&E | D35: ='Income Statement'!C11/'Balance Sheet'!C30 -> 12.629431 | E35: ='Income Statement'!D11/'Balance Sheet'!D30 -> 13.425242 | F35: ='Income Statement'!E11/'Balance Sheet'!E30 -> 11.498316 | G35: ='Income Statement'!F11/'Balance Sheet'!F30 -> 12.751308 | H35: ='Income Statement'!G11/'Balance Sheet'!G30 -> 12.471026
B37: E. MARKET / PER-SHARE RATIOS
B38: Basic EPS (Rs.) | D38: ='Income Statement'!C35 -> 5.9380137 | E38: ='Income Statement'!D35 -> 4.2182055 | F38: ='Income Statement'!E35 -> 1.0307775 | G38: ='Income Statement'!F35 -> 8.9493924 | H38: ='Income Statement'!G35 -> 7.5774084
B39: Book Value per Share (Rs.) | C39: Net Worth / Shares Outstanding | D39: ='Balance Sheet'!C13/'Income Statement'!C34 -> 58.422306 | E39: ='Balance Sheet'!D13/'Income Statement'!D34 -> 62.67557 | F39: ='Balance Sheet'!E13/'Income Statement'!E34 -> 63.826848 | G39: ='Balance Sheet'!F13/'Income Statement'!F34 -> 72.481157 | H39: ='Balance Sheet'!G13/'Income Statement'!G34 -> 80.33241

Sheet Trend Analysis
B2: AWL AGRIBUSINESS LIMITED
B3: TREND ANALYSIS
B4: Base Year: FY2021-22 = 100
B6: Particulars | C6: FY2021-22 | D6: FY2022-23 | E6: FY2023-24 | F6: FY2024-25 | G6: FY2025-26
B8: INCOME STATEMENT TRENDS
B9: Revenue from Operations | C9: =IFERROR(('Income Statement'!C10)/('Income Statement'!$C$10)*100,"n/m") -> 100 | D9: =IFERROR(('Income Statement'!D10)/('Income Statement'!$C$10)*100,"n/m") -> 107.4416 | E9: =IFERROR(('Income Statement'!E10)/('Income Statement'!$C$10)*100,"n/m") -> 94.589604 | F9: =IFERROR(('Income Statement'!F10)/('Income Statement'!$C$10)*100,"n/m") -> 117.57363 | G9: =IFERROR(('Income Statement'!G10)/('Income Statement'!$C$10)*100,"n/m") -> 137.99465
B10: Operating Profit | C10: =IFERROR(('Income Statement'!C21)/('Income Statement'!$C$21)*100,"n/m") -> 100 | D10: =IFERROR(('Income Statement'!D21)/('Income Statement'!$C$21)*100,"n/m") -> 55.186528 | E10: =IFERROR(('Income Statement'!E21)/('Income Statement'!$C$21)*100,"n/m") -> 63.270006 | F10: =IFERROR(('Income Statement'!F21)/('Income Statement'!$C$21)*100,"n/m") -> 142.86701 | G10: =IFERROR(('Income Statement'!G21)/('Income Statement'!$C$21)*100,"n/m") -> 122.71272
B11: EBITDA | C11: =IFERROR(('Income Statement'!C25)/('Income Statement'!$C$25)*100,"n/m") -> 100 | D11: =IFERROR(('Income Statement'!D25)/('Income Statement'!$C$25)*100,"n/m") -> 100.55474 | E11: =IFERROR(('Income Statement'!E25)/('Income Statement'!$C$25)*100,"n/m") -> 70.141435 | F11: =IFERROR(('Income Statement'!F25)/('Income Statement'!$C$25)*100,"n/m") -> 142.2001 | G11: =IFERROR(('Income Statement'!G25)/('Income Statement'!$C$25)*100,"n/m") -> 132.19068
B12: Profit Before Tax | C12: =IFERROR(('Income Statement'!C28)/('Income Statement'!$C$28)*100,"n/m") -> 100 | D12: =IFERROR(('Income Statement'!D28)/('Income Statement'!$C$28)*100,"n/m") -> 74.276676 | E12: =IFERROR(('Income Statement'!E28)/('Income Statement'!$C$28)*100,"n/m") -> 21.340888 | F12: =IFERROR(('Income Statement'!F28)/('Income Statement'!$C$28)*100,"n/m") -> 150.67044 | G12: =IFERROR(('Income Statement'!G28)/('Income Statement'!$C$28)*100,"n/m") -> 129.13314
B13: Net Profit After Tax | C13: =IFERROR(('Income Statement'!C31)/('Income Statement'!$C$31)*100,"n/m") -> 100 | D13: =IFERROR(('Income Statement'!D31)/('Income Statement'!$C$31)*100,"n/m") -> 71.09188 | E13: =IFERROR(('Income Statement'!E31)/('Income Statement'!$C$31)*100,"n/m") -> 17.372295 | F13: =IFERROR(('Income Statement'!F31)/('Income Statement'!$C$31)*100,"n/m") -> 150.51677 | G13: =IFERROR(('Income Statement'!G31)/('Income Statement'!$C$31)*100,"n/m") -> 127.38303
B14: Basic EPS | C14: =IFERROR(('Income Statement'!C35)/('Income Statement'!$C$35)*100,"n/m") -> 100 | D14: =IFERROR(('Income Statement'!D35)/('Income Statement'!$C$35)*100,"n/m") -> 71.037316 | E14: =IFERROR(('Income Statement'!E35)/('Income Statement'!$C$35)*100,"n/m") -> 17.358961 | F14: =IFERROR(('Income Statement'!F35)/('Income Statement'!$C$35)*100,"n/m") -> 150.71357 | G14: =IFERROR(('Income Statement'!G35)/('Income Statement'!$C$35)*100,"n/m") -> 127.60847
B16: BALANCE SHEET TRENDS
B17: Total Shareholders' Equity | C17: =IFERROR(('Balance Sheet'!C13)/('Balance Sheet'!$C$13)*100,"n/m") -> 100 | D17: =IFERROR(('Balance Sheet'!D13)/('Balance Sheet'!$C$13)*100,"n/m") -> 107.36261 | E17: =IFERROR(('Balance Sheet'!E13)/('Balance Sheet'!$C$13)*100,"n/m") -> 109.33474 | F17: =IFERROR(('Balance Sheet'!F13)/('Balance Sheet'!$C$13)*100,"n/m") -> 123.90218 | G17: =IFERROR(('Balance Sheet'!G13)/('Balance Sheet'!$C$13)*100,"n/m") -> 137.26006
B18: Total Borrowings (LT + ST) | C18: =IFERROR(('Balance Sheet'!C16+'Balance Sheet'!C21)/('Balance Sheet'!C16+'Balance Sheet'!C21)*100,"n/m") -> 100 | D18: =IFERROR(('Balance Sheet'!D16+'Balance Sheet'!D21)/('Balance Sheet'!C16+'Balance Sheet'!C21)*100,"n/m") -> 86.644314 | E18: =IFERROR(('Balance Sheet'!E16+'Balance Sheet'!E21)/('Balance Sheet'!C16+'Balance Sheet'!C21)*100,"n/m") -> 94.043155 | F18: =IFERROR(('Balance Sheet'!F16+'Balance Sheet'!F21)/('Balance Sheet'!C16+'Balance Sheet'!C21)*100,"n/m") -> 66.660825 | G18: =IFERROR(('Balance Sheet'!G16+'Balance Sheet'!G21)/('Balance Sheet'!C16+'Balance Sheet'!C21)*100,"n/m") -> 31.860575
B19: Total Assets | C19: =IFERROR(('Balance Sheet'!C41)/('Balance Sheet'!$C$41)*100,"n/m") -> 100 | D19: =IFERROR(('Balance Sheet'!D41)/('Balance Sheet'!$C$41)*100,"n/m") -> 98.419102 | E19: =IFERROR(('Balance Sheet'!E41)/('Balance Sheet'!$C$41)*100,"n/m") -> 92.908008 | F19: =IFERROR(('Balance Sheet'!F41)/('Balance Sheet'!$C$41)*100,"n/m") -> 105.25881 | G19: =IFERROR(('Balance Sheet'!G41)/('Balance Sheet'!$C$41)*100,"n/m") -> 116.12596
B20: Inventories | C20: =IFERROR(('Balance Sheet'!C35)/('Balance Sheet'!$C$35)*100,"n/m") -> 100 | D20: =IFERROR(('Balance Sheet'!D35)/('Balance Sheet'!$C$35)*100,"n/m") -> 99.546397 | E20: =IFERROR(('Balance Sheet'!E35)/('Balance Sheet'!$C$35)*100,"n/m") -> 93.351477 | F20: =IFERROR(('Balance Sheet'!F35)/('Balance Sheet'!$C$35)*100,"n/m") -> 111.99171 | G20: =IFERROR(('Balance Sheet'!G35)/('Balance Sheet'!$C$35)*100,"n/m") -> 106.15241
B21: Trade Receivables | C21: =IFERROR(('Balance Sheet'!C36)/('Balance Sheet'!$C$36)*100,"n/m") -> 100 | D21: =IFERROR(('Balance Sheet'!D36)/('Balance Sheet'!$C$36)*100,"n/m") -> 87.060415 | E21: =IFERROR(('Balance Sheet'!E36)/('Balance Sheet'!$C$36)*100,"n/m") -> 80.342651 | F21: =IFERROR(('Balance Sheet'!F36)/('Balance Sheet'!$C$36)*100,"n/m") -> 108.90667 | G21: =IFERROR(('Balance Sheet'!G36)/('Balance Sheet'!$C$36)*100,"n/m") -> 118.31921
B23: CASH FLOW TRENDS
B24: Cash Flow from Operations | C24: =IFERROR(('Cash Flow Statement'!C9)/('Cash Flow Statement'!$C$9)*100,"n/m") -> 100 | D24: =IFERROR(('Cash Flow Statement'!D9)/('Cash Flow Statement'!$C$9)*100,"n/m") -> 55.342237 | E24: =IFERROR(('Cash Flow Statement'!E9)/('Cash Flow Statement'!$C$9)*100,"n/m") -> 24.123539 | F24: =IFERROR(('Cash Flow Statement'!F9)/('Cash Flow Statement'!$C$9)*100,"n/m") -> 179.46578 | G24: =IFERROR(('Cash Flow Statement'!G9)/('Cash Flow Statement'!$C$9)*100,"n/m") -> 327.8798
B26: All series are re-based so that the value in the base year (FY2021-22) equals 100; subsequent years show cumulative growth/decline relative to that base.

Sheet Key Indicators
B2: AWL AGRIBUSINESS LIMITED
B3: Key Indicators
B4: FY: FY2021-22 – FY2025-26 | Rs. in Crores
B6: Revenue (FY26) | C6: Net Profit (FY26) | D6: EBITDA Margin (FY26) | E6: ROE (FY26) | F6: Current Ratio (FY26) | G6: Basic EPS (FY26)
B7: ='Income Statement'!G10 -> 74731 | C7: ='Income Statement'!G31 -> 984.76 | D7: ='Income Statement'!G25/'Income Statement'!G11 -> 0.033768048 | E7: ='Income Statement'!G31/'Balance Sheet'!G13 -> 0.09432567 | F7: ='Balance Sheet'!G39/'Balance Sheet'!G24 -> 1.2596831 | G7: ='Income Statement'!G35 -> 7.5774084
B9: Chart Data Reference
B10: Year | C10: FY2021-22 | D10: FY2022-23 | E10: FY2023-24 | F10: FY2024-25 | G10: FY2025-26
B11: Revenue | C11: ='Income Statement'!C10 -> 54155 | D11: ='Income Statement'!D10 -> 58185 | E11: ='Income Statement'!E10 -> 51225 | F11: ='Income Statement'!F10 -> 63672 | G11: ='Income Statement'!G10 -> 74731
B12: Net Profit | C12: ='Income Statement'!C31 -> 773.07 | D12: ='Income Statement'!D31 -> 549.59 | E12: ='Income Statement'!E31 -> 134.3 | F12: ='Income Statement'!F31 -> 1163.6 | G12: ='Income Statement'!G31 -> 984.76
B13: EBITDA | C13: ='Income Statement'!C25 -> 1909 | D13: ='Income Statement'!D25 -> 1919.59 | E13: ='Income Statement'!E25 -> 1339 | F13: ='Income Statement'!F25 -> 2714.6 | G13: ='Income Statement'!G25 -> 2523.52
B14: Net Profit Margin % | C14: ='Income Statement'!C31/'Income Statement'!C11 -> 0.014275136 | D14: ='Income Statement'!D31/'Income Statement'!D11 -> 0.0094455616 | E14: ='Income Statement'!E31/'Income Statement'!E11 -> 0.0026217667 | F14: ='Income Statement'!F31/'Income Statement'!F11 -> 0.018274909 | G14: ='Income Statement'!G31/'Income Statement'!G11 -> 0.013177396
B15: Total Borrowings | C15: ='Balance Sheet'!C16+'Balance Sheet'!C21 -> 2567.97 | D15: ='Balance Sheet'!D16+'Balance Sheet'!D21 -> 2225 | E15: ='Balance Sheet'!E16+'Balance Sheet'!E21 -> 2415 | F15: ='Balance Sheet'!F16+'Balance Sheet'!F21 -> 1711.83 | G15: ='Balance Sheet'!G16+'Balance Sheet'!G21 -> 818.17
B16: Shareholders' Equity | C16: ='Balance Sheet'!C13 -> 7606 | D16: ='Balance Sheet'!D13 -> 8166 | E16: ='Balance Sheet'!E13 -> 8316 | F16: ='Balance Sheet'!F13 -> 9424 | G16: ='Balance Sheet'!G13 -> 10440
B17: Cash Flow from Ops | C17: ='Cash Flow Statement'!C9 -> 1198 | D17: ='Cash Flow Statement'!D9 -> 663 | E17: ='Cash Flow Statement'!E9 -> 289 | F17: ='Cash Flow Statement'!F9 -> 2150 | G17: ='Cash Flow Statement'!G9 -> 3928
B18: Return on Equity % | C18: ='Income Statement'!C31/'Balance Sheet'!C13 -> 0.1016395 | D18: ='Income Statement'!D31/'Balance Sheet'!D13 -> 0.067302229 | E18: ='Income Statement'!E31/'Balance Sheet'!E13 -> 0.016149591 | F18: ='Income Statement'!F31/'Balance Sheet'!F13 -> 0.12347199 | G18: ='Income Statement'!G31/'Balance Sheet'!G13 -> 0.09432567
B19: Current Ratio | C19: ='Balance Sheet'!C39/'Balance Sheet'!C24 -> 1.21204 | D19: ='Balance Sheet'!D39/'Balance Sheet'!D24 -> 1.2433473 | E19: ='Balance Sheet'!E39/'Balance Sheet'!E24 -> 1.2216138 | F19: ='Balance Sheet'!F39/'Balance Sheet'!F24 -> 1.246286 | G19: ='Balance Sheet'!G39/'Balance Sheet'!G24 -> 1.2596831
B20: Cash Conversion Cycle (Days) | C20: ='Ratio Analysis'!D34 -> 58.923949 | D20: ='Ratio Analysis'!E34 -> 46.642623 | E20: ='Ratio Analysis'!F34 -> 48.048698 | F20: ='Ratio Analysis'!G34 -> 50.814182 | G20: ='Ratio Analysis'!H34 -> 39.667095

Sheet Notes
B2: AWL AGRIBUSINESS LIMITED
B3: NOTES, ASSUMPTIONS & SOURCES
B5: Topic | C5: Detail
B6: Company | C6: AWL Agri Business Ltd was formerly known as Adani Wilmar Ltd. The Adani Group exited the joint venture in FY24; the company was renamed 'AWL Agri Business Ltd' following a shareholder vote. NSE: AWL, BSE: 543458, ISIN: INE699H01024.
B7: Basis of Preparation | C7: All figures are Consolidated financial statements, presented in Rs. Crores, for the five financial years FY2021-22 through FY2025-26 (Indian fiscal year ending 31 March).
B8: Scope of This Workbook | C8: The Income Statement, Balance Sheet, and Cash Flow Statement tabs (and the Cover tab) contain the underlying figures and were prepared/finalised separately. This workbook adds the six analytical tabs Common Size Analysis, Comparative Analysis, Ratio Analysis, Trend Analysis, Charts & Dashboard, and these Notes all built as live formulas linked to those three source statements. No cell on the Income Statement, Balance Sheet, or Cash Flow Statement tabs was modified.
B9: Balance Sheet Row Label Note | C9: On the Balance Sheet tab, the subtotal at row 32 is labeled 'Total Current Assets' but its formula (=PP&E + Other Non-Current Assets) actually computes Total Non-Current Assets; the true Total Current Assets subtotal is at row 39 (Inventories + Trade Receivables + Cash + Other Current Assets). All formulas in this workbook's analytical tabs reference the correct underlying figures by formula logic, not by the row label, so results are accurate but you may want to correct the row-32 label on the Balance Sheet tab for clarity.
B10: Liquidity Ratios | C10: Because the Balance Sheet tab now separates Current Liabilities (Short-Term Borrowings, Trade Payables, Other Current Liabilities & Provisions) from Current Assets (Inventories, Trade Receivables, Cash & Equivalents, Other Current Assets), Current Ratio, Quick Ratio and Cash Ratio are computed directly by formula on the Ratio Analysis tab rather than estimated.
B11: Cash Conversion Cycle | C11: Debtor Days, Inventory Days, Payable Days and the resulting Cash Conversion Cycle are now computed by formula (using average-free, year-end balances, per standard convention) rather than hardcoded, since the Balance Sheet tab provides Trade Receivables, Inventories and Trade Payables as discrete line items. COGS is proxied as Cost of Materials Consumed + Purchases of Stock-in-Trade + Changes in Inventories, per the Income Statement tab's expense breakup.
B12: Total Borrowings | C12: Wherever 'Total Borrowings' is used (Debt-to-Equity, Debt-to-Assets, Comparative & Trend Analysis, Dashboard), it is computed as Long-Term Borrowings + Short-Term Borrowings from the Balance Sheet tab.
B13: Effective Tax Rate | C13: Tax Expense is taken directly from the Income Statement tab as disclosed for each year; it reflects the company's blended effective tax rate, not the Indian statutory corporate tax rate.
B14: Free Cash Flow | C14: Reported as disclosed on the Cash Flow Statement tab (CFO less capital expenditure, as originally compiled) rather than re-derived, since a clean capex sub-line is not separately broken out from other investing cash flows.
B15: Common Size Analysis Basis | C15: Income Statement items are expressed as % of Total Revenue (Revenue from Operations). Balance Sheet items are expressed as % of Total Assets.
B16: Comparative / Trend Analysis | C16: Comparative Analysis shows year-on-year Rs. and % change for consecutive year-pairs. Trend Analysis indexes each series to the earliest year shown (FY2021-22 = 100) to visualize cumulative growth or decline over the period.
... B18: Data Accuracy Disclaimer | C18: Figures on the source statement tabs were compiled from public company filings / financial-data aggregators and have not been independently re-verified against the company's original signed Annual Report for this update. Users should cross-check against the official Annual Report (available at www.awl.in) before relying on this workbook for investment, credit, or reporting decisions.
